solana_agent_kit/__init__.py
solana_agent_kit/agent/__init__.py
solana_agent_kit/constants/__init__.py
solana_agent_kit/helpers/__init__.py
solana_agent_kit/langchain/__init__.py
solana_agent_kit/tools/__init__.py
solana_agent_kit/tools/burn_and_close_account.py
solana_agent_kit/tools/create_gibwork.py
solana_agent_kit/tools/create_image.py
solana_agent_kit/tools/create_meteora_dlmm_pool.py
solana_agent_kit/tools/deploy_token.py
solana_agent_kit/tools/fetch_price.py
solana_agent_kit/tools/get_balance.py
solana_agent_kit/tools/get_token_data.py
solana_agent_kit/tools/get_tps.py
solana_agent_kit/tools/launch_pumpfun_token.py
solana_agent_kit/tools/lend.py
solana_agent_kit/tools/request_faucet_funds.py
solana_agent_kit/tools/rugcheck.py
solana_agent_kit/tools/stake_with_jup.py
solana_agent_kit/tools/trade.py
solana_agent_kit/tools/transfer.py
solana_agent_kit/tools/use_3land.py
solana_agent_kit/tools/use_adrena.py
solana_agent_kit/tools/use_alldomains.py
solana_agent_kit/tools/use_backpack.py
solana_agent_kit/tools/use_cybers.py
solana_agent_kit/tools/use_debridge.py
solana_agent_kit/tools/use_drift.py
solana_agent_kit/tools/use_flash.py
solana_agent_kit/tools/use_helius.py
solana_agent_kit/tools/use_jito.py
solana_agent_kit/tools/use_metaplex.py
solana_agent_kit/tools/use_moonshot.py
solana_agent_kit/tools/use_pumpfun.py
solana_agent_kit/tools/use_pyth.py
solana_agent_kit/tools/use_raydium.py
solana_agent_kit/tools/use_sns.py
solana_agent_kit/types/__init__.py
solana_agent_kit/utils/__init__.py
solana_agent_kit/utils/agentipy_proxy/__init__.py
solana_agent_kit/utils/agentipy_proxy/constants.py
solana_agent_kit/utils/agentipy_proxy/utils.py
solana_agent_kit/utils/helius/__init__.py
solana_agent_kit/utils/helius/helpers/__init__.py
solana_agent_kit/utils/helius/helpers/utility.py
solana_agent_kit/utils/jito/__init__.py
solana_agent_kit/utils/keypair.py
solana_agent_kit/utils/meteora_dlmm/__init__.py
solana_agent_kit/utils/meteora_dlmm/constants.py
solana_agent_kit_py-1.4.0.dist-info/LICENSE.md
solana_agent_kit_py-1.4.0.dist-info/METADATA
solana_agent_kit_py-1.4.0.dist-info/WHEEL
solana_agent_kit_py-1.4.0.dist-info/RECORD
