Metadata-Version: 2.3
Name: solana-agent-kit-py
Version: 1.4.0
Summary: connect any ai agents to solana protocols
License: Apache-2.0
Keywords: solana,sdk,blockchain,tools
Author: sendaifun
Author-email: dev@sendaifun.com
Requires-Python: ==3.13.0
Classifier: License :: OSI Approved :: Apache Software License
Classifier: Programming Language :: Python :: 3
Classifier: Programming Language :: Python :: 3.13
Requires-Dist: aiohttp (>=3.11.11,<4.0.0)
Requires-Dist: anchorpy (>=0.20.1,<0.21.0)
Requires-Dist: backpack-exchange-sdk (>=1.0.24,<2.0.0)
Requires-Dist: base58 (>=2.1.1,<3.0.0)
Requires-Dist: cryptography (>=44.0.0,<45.0.0)
Requires-Dist: langchain (>=0.3.12,<0.4.0)
Requires-Dist: numpy (>=1.26.2,<2.0.0)
Requires-Dist: openai (>=1.58.1,<2.0.0)
Requires-Dist: pillow (>=11.0.0,<12.0.0)
Requires-Dist: pre-commit (>=4.0.1,<5.0.0)
Requires-Dist: pydantic (>=2.10.4,<3.0.0)
Requires-Dist: pydantic-ai (>=0.0.19)
Requires-Dist: pynacl (>=1.5.0,<2.0.0)
Requires-Dist: pythclient (>=0.2.0,<0.3.0)
Requires-Dist: python-dotenv (>=1.0.1,<2.0.0)
Requires-Dist: requests (==2.32.3)
Requires-Dist: setuptools (>=75.6.0,<76.0.0)
Requires-Dist: solana (>=0.35.0,<0.36.0)
Requires-Dist: solders (>=0.21.0,<0.22.0)
Requires-Dist: sphinx (>=8.1.3,<9.0.0)
Requires-Dist: sphinx-autodoc-typehints (>=2.5.0,<3.0.0)
Requires-Dist: sphinx-rtd-theme (>=3.0.2,<4.0.0)
Requires-Dist: twine (>=6.0.1,<7.0.0)
Requires-Dist: wheel (>=0.45.1,<0.46.0)
Project-URL: Homepage, https://github.com/sendaifun/solana-agent-kit-py
Project-URL: Repository, https://github.com/sendaifun/solana-agent-kit-py
